pattern_printing-0.1.0.dist-info/licenses/LICENSE
publish/__init__.py
publish/file1.py
pattern_printing-0.1.0.dist-info/METADATA
pattern_printing-0.1.0.dist-info/WHEEL
pattern_printing-0.1.0.dist-info/top_level.txt
pattern_printing-0.1.0.dist-info/RECORD
