Metadata-Version: 2.4
Name: Pattern_Printing
Version: 0.1.0
Summary: Sample Test Package
Home-page: https://github.com/prachikabra121/prachi-test-package
Author: Sagar Pol
Author-email: sagpol03@gmail.com
Classifier: Programming Language :: Python :: 3
Classifier: License :: OSI Approved :: MIT License
Classifier: Operating System :: OS Independent
Requires-Python: >=3.6
License-File: LICENSE
Dynamic: author
Dynamic: author-email
Dynamic: classifier
Dynamic: description
Dynamic: description-content-type
Dynamic: home-page
Dynamic: license-file
Dynamic: requires-python
Dynamic: summary
